{
    "data": [
        {
            "update_time": "2025-03-12 15:59",
            "water_storage": "267.8535148780477 %"
        },
        {
            "update_time": "2025-03-12 16:59",
            "water_storage": "267.8477124390233 %"
        },
        {
            "update_time": "2025-03-12 18:00",
            "water_storage": "267.8423071341453 %"
        },
        {
            "update_time": "2025-03-12 19:00",
            "water_storage": "267.8369018292673 %"
        },
        {
            "update_time": "2025-03-12 20:00",
            "water_storage": "267.83149652438925 %"
        },
        {
            "update_time": "2025-03-12 21:17",
            "water_storage": "267.8259580487795 %"
        },
        {
            "update_time": "2025-03-12 22:00",
            "water_storage": "267.8205527439015 %"
        },
        {
            "update_time": "2025-03-12 23:00",
            "water_storage": "267.8154114024381 %"
        },
        {
            "update_time": "2025-03-13 00:00",
            "water_storage": "267.8104008536576 %"
        },
        {
            "update_time": "2025-03-13 00:59",
            "water_storage": "267.8053903048771 %"
        },
        {
            "update_time": "2025-03-13 02:00",
            "water_storage": "267.8003797560966 %"
        },
        {
            "update_time": "2025-03-13 03:00",
            "water_storage": "267.7953692073161 %"
        },
        {
            "update_time": "2025-03-13 03:59",
            "water_storage": "267.79035865853564 %"
        },
        {
            "update_time": "2025-03-13 04:59",
            "water_storage": "267.78534810975515 %"
        },
        {
            "update_time": "2025-03-13 05:59",
            "water_storage": "267.78033756097466 %"
        },
        {
            "update_time": "2025-03-13 06:59",
            "water_storage": "267.77532701219417 %"
        },
        {
            "update_time": "2025-03-13 08:00",
            "water_storage": "267.77018567073077 %"
        },
        {
            "update_time": "2025-03-13 10:15",
            "water_storage": "268.77018567073077 %"
        },
        {
            "update_time": "2025-03-13 11:19",
            "water_storage": "285.27018567073077 %"
        },
        {
            "update_time": "2025-03-13 12:00",
            "water_storage": "286.27018567073077 %"
        },
        {
            "update_time": "2025-03-13 13:00",
            "water_storage": "286.2644426829259 %"
        },
        {
            "update_time": "2025-03-13 14:00",
            "water_storage": "286.2591681707308 %"
        },
        {
            "update_time": "2025-03-13 14:59",
            "water_storage": "287.7591681707308 %"
        },
        {
            "update_time": "2025-03-13 16:00",
            "water_storage": "294.2591681707308 %"
        }
    ]
}