{
    "data": [
        {
            "update_time": "2025-03-10 18:59",
            "water_storage": "268.0581911585354 %"
        },
        {
            "update_time": "2025-03-10 19:59",
            "water_storage": "268.05342554877933 %"
        },
        {
            "update_time": "2025-03-10 21:17",
            "water_storage": "268.04871701219395 %"
        },
        {
            "update_time": "2025-03-10 22:00",
            "water_storage": "268.04489548780373 %"
        },
        {
            "update_time": "2025-03-10 23:00",
            "water_storage": "268.0410739634135 %"
        },
        {
            "update_time": "2025-03-11 00:00",
            "water_storage": "268.0366888414623 %"
        },
        {
            "update_time": "2025-03-11 01:00",
            "water_storage": "268.03300048780375 %"
        },
        {
            "update_time": "2025-03-11 02:00",
            "water_storage": "268.0293121341452 %"
        },
        {
            "update_time": "2025-03-11 03:00",
            "water_storage": "268.0257545731696 %"
        },
        {
            "update_time": "2025-03-11 04:00",
            "water_storage": "268.022197012194 %"
        },
        {
            "update_time": "2025-03-11 05:00",
            "water_storage": "268.0186394512184 %"
        },
        {
            "update_time": "2025-03-11 06:00",
            "water_storage": "268.01495109755984 %"
        },
        {
            "update_time": "2025-03-11 07:00",
            "water_storage": "268.0112627439013 %"
        },
        {
            "update_time": "2025-03-11 07:59",
            "water_storage": "268.00744121951107 %"
        },
        {
            "update_time": "2025-03-11 10:14",
            "water_storage": "268.0026946341452 %"
        },
        {
            "update_time": "2025-03-11 11:19",
            "water_storage": "267.9976840853647 %"
        },
        {
            "update_time": "2025-03-11 11:59",
            "water_storage": "267.9925427439013 %"
        },
        {
            "update_time": "2025-03-11 13:00",
            "water_storage": "267.9872682317062 %"
        },
        {
            "update_time": "2025-03-11 14:00",
            "water_storage": "267.9815989634135 %"
        },
        {
            "update_time": "2025-03-11 15:00",
            "water_storage": "267.9753993902428 %"
        },
        {
            "update_time": "2025-03-11 15:59",
            "water_storage": "267.96933298780374 %"
        },
        {
            "update_time": "2025-03-11 17:00",
            "water_storage": "267.9639276829257 %"
        },
        {
            "update_time": "2025-03-11 17:59",
            "water_storage": "267.9589171341452 %"
        },
        {
            "update_time": "2025-03-11 19:00",
            "water_storage": "267.9543037195111 %"
        }
    ]
}