{
    "data": [
        {
            "update_time": "2024-12-31 23:00",
            "water_storage": "102.04556012195087 %"
        },
        {
            "update_time": "2024-12-31 23:59",
            "water_storage": "102.04213573170696 %"
        },
        {
            "update_time": "2025-01-01 01:00",
            "water_storage": "102.03871134146306 %"
        },
        {
            "update_time": "2025-01-01 02:00",
            "water_storage": "102.03528695121915 %"
        },
        {
            "update_time": "2025-01-01 03:00",
            "water_storage": "102.03172939024354 %"
        },
        {
            "update_time": "2025-01-01 04:00",
            "water_storage": "102.02817182926793 %"
        },
        {
            "update_time": "2025-01-01 05:00",
            "water_storage": "102.02461426829232 %"
        },
        {
            "update_time": "2025-01-01 05:59",
            "water_storage": "102.02105670731672 %"
        },
        {
            "update_time": "2025-01-01 07:00",
            "water_storage": "102.01736835365818 %"
        },
        {
            "update_time": "2025-01-01 07:59",
            "water_storage": "102.01354682926794 %"
        },
        {
            "update_time": "2025-01-01 10:16",
            "water_storage": "102.00933054878013 %"
        },
        {
            "update_time": "2025-01-01 11:19",
            "water_storage": "102.00511426829232 %"
        },
        {
            "update_time": "2025-01-01 12:00",
            "water_storage": "102.00102878048745 %"
        },
        {
            "update_time": "2025-01-01 12:59",
            "water_storage": "101.99694329268257 %"
        },
        {
            "update_time": "2025-01-01 13:59",
            "water_storage": "101.99312176829233 %"
        },
        {
            "update_time": "2025-01-01 15:00",
            "water_storage": "101.98930024390208 %"
        },
        {
            "update_time": "2025-01-01 16:00",
            "water_storage": "101.98547871951183 %"
        },
        {
            "update_time": "2025-01-01 17:00",
            "water_storage": "102.48547871951183 %"
        },
        {
            "update_time": "2025-01-01 18:00",
            "water_storage": "102.48165719512158 %"
        },
        {
            "update_time": "2025-01-01 19:00",
            "water_storage": "102.47783567073134 %"
        },
        {
            "update_time": "2025-01-01 20:00",
            "water_storage": "102.97783567073134 %"
        },
        {
            "update_time": "2025-01-01 21:12",
            "water_storage": "104.47783567073134 %"
        },
        {
            "update_time": "2025-01-01 22:00",
            "water_storage": "105.97783567073134 %"
        },
        {
            "update_time": "2025-01-01 22:59",
            "water_storage": "106.47783567073134 %"
        }
    ]
}