{
    "data": [
        {
            "update_time": "2025-01-28 13:00",
            "water_storage": "125.85488018292659 %"
        },
        {
            "update_time": "2025-01-28 14:00",
            "water_storage": "125.85083036585343 %"
        },
        {
            "update_time": "2025-01-28 15:00",
            "water_storage": "125.8471420121949 %"
        },
        {
            "update_time": "2025-01-28 15:59",
            "water_storage": "125.84358445121929 %"
        },
        {
            "update_time": "2025-01-28 17:00",
            "water_storage": "125.84016006097538 %"
        },
        {
            "update_time": "2025-01-28 18:00",
            "water_storage": "125.83699963414611 %"
        },
        {
            "update_time": "2025-01-28 19:00",
            "water_storage": "125.83410317073148 %"
        },
        {
            "update_time": "2025-01-28 20:00",
            "water_storage": "125.83120670731685 %"
        },
        {
            "update_time": "2025-01-28 21:13",
            "water_storage": "125.82844341463392 %"
        },
        {
            "update_time": "2025-01-28 21:59",
            "water_storage": "125.825680121951 %"
        },
        {
            "update_time": "2025-01-28 23:00",
            "water_storage": "125.82291682926807 %"
        },
        {
            "update_time": "2025-01-29 00:00",
            "water_storage": "125.82015353658514 %"
        },
        {
            "update_time": "2025-01-29 01:00",
            "water_storage": "125.81752103658513 %"
        },
        {
            "update_time": "2025-01-29 02:00",
            "water_storage": "125.81488853658513 %"
        },
        {
            "update_time": "2025-01-29 03:00",
            "water_storage": "125.81225603658513 %"
        },
        {
            "update_time": "2025-01-29 04:00",
            "water_storage": "125.80962353658512 %"
        },
        {
            "update_time": "2025-01-29 05:00",
            "water_storage": "125.80699103658512 %"
        },
        {
            "update_time": "2025-01-29 06:00",
            "water_storage": "125.80435853658511 %"
        },
        {
            "update_time": "2025-01-29 07:00",
            "water_storage": "125.80159524390218 %"
        },
        {
            "update_time": "2025-01-29 07:59",
            "water_storage": "125.79869878048756 %"
        },
        {
            "update_time": "2025-01-29 10:05",
            "water_storage": "125.79514121951195 %"
        },
        {
            "update_time": "2025-01-29 11:08",
            "water_storage": "125.79118890243878 %"
        },
        {
            "update_time": "2025-01-29 12:00",
            "water_storage": "125.7871034146339 %"
        },
        {
            "update_time": "2025-01-29 13:00",
            "water_storage": "125.7827539634144 %"
        }
    ]
}