{
    "data": [
        {
            "update_time": "2025-02-16 13:00",
            "water_storage": "181.97159536585252 %"
        },
        {
            "update_time": "2025-02-16 14:00",
            "water_storage": "181.96658481707203 %"
        },
        {
            "update_time": "2025-02-16 15:00",
            "water_storage": "181.96170743902326 %"
        },
        {
            "update_time": "2025-02-16 16:00",
            "water_storage": "181.9569608536574 %"
        },
        {
            "update_time": "2025-02-16 17:00",
            "water_storage": "181.95248060975496 %"
        },
        {
            "update_time": "2025-02-16 18:00",
            "water_storage": "181.94826432926715 %"
        },
        {
            "update_time": "2025-02-16 19:00",
            "water_storage": "181.94417884146227 %"
        },
        {
            "update_time": "2025-02-16 20:00",
            "water_storage": "181.9400933536574 %"
        },
        {
            "update_time": "2025-02-16 21:10",
            "water_storage": "181.93614103658425 %"
        },
        {
            "update_time": "2025-02-16 22:00",
            "water_storage": "181.9321887195111 %"
        },
        {
            "update_time": "2025-02-16 23:00",
            "water_storage": "181.92836719512084 %"
        },
        {
            "update_time": "2025-02-17 00:00",
            "water_storage": "181.92441487804768 %"
        },
        {
            "update_time": "2025-02-17 01:00",
            "water_storage": "181.92046256097453 %"
        },
        {
            "update_time": "2025-02-17 02:00",
            "water_storage": "181.91664103658428 %"
        },
        {
            "update_time": "2025-02-17 02:59",
            "water_storage": "181.91281951219403 %"
        },
        {
            "update_time": "2025-02-17 04:00",
            "water_storage": "181.9089979878038 %"
        },
        {
            "update_time": "2025-02-17 05:00",
            "water_storage": "181.90517646341354 %"
        },
        {
            "update_time": "2025-02-17 06:00",
            "water_storage": "181.901488109755 %"
        },
        {
            "update_time": "2025-02-17 07:00",
            "water_storage": "181.89766658536476 %"
        },
        {
            "update_time": "2025-02-17 08:00",
            "water_storage": "181.8937142682916 %"
        },
        {
            "update_time": "2025-02-17 10:11",
            "water_storage": "181.88910085365745 %"
        },
        {
            "update_time": "2025-02-17 11:14",
            "water_storage": "181.88422347560868 %"
        },
        {
            "update_time": "2025-02-17 12:00",
            "water_storage": "181.8792129268282 %"
        },
        {
            "update_time": "2025-02-17 13:00",
            "water_storage": "181.8742023780477 %"
        }
    ]
}